Metadata-Version: 1.1
Name: sherlock.py
Version: 0.3.0
Summary: Python to shell script transcompiler
Home-page: https://github.com/Luavis/sherlock
Author: Luavis Kang
Author-email: luaviskang@gmail.com
License: MIT
Platform: POSIX
Classifier: Development Status :: 2 - Pre-Alpha
Classifier: License :: OSI Approved :: MIT License
Classifier: Environment :: Console
Classifier: Operating System :: POSIX
Classifier: Operating System :: MacOS :: MacOS X
Classifier: Topic :: Software Development :: Compilers
Classifier: Programming Language :: Python
Classifier: Programming Language :: Python :: 2.6
Classifier: Programming Language :: Python :: 2.7
Classifier: Programming Language :: Python :: 3.3
Classifier: Programming Language :: Python :: 3.4
Classifier: Programming Language :: Python :: 3.5
Classifier: Programming Language :: Python :: 3.6
